nnfigs/__init__.py
nnfigs/core.py
nnfigs-0.2.2.dist-info/AUTHORS
nnfigs-0.2.2.dist-info/LICENSE
nnfigs-0.2.2.dist-info/METADATA
nnfigs-0.2.2.dist-info/WHEEL
nnfigs-0.2.2.dist-info/top_level.txt
nnfigs-0.2.2.dist-info/RECORD
