Metadata-Version: 2.1
Name: nnfigs
Version: 0.2.2
Summary: Draw neural network figures with Matplotlib
Author-email: Jérémie DECOCK <jd.jdhp@gmail.com>
Classifier: Development Status :: 4 - Beta
Classifier: Intended Audience :: Developers
Classifier: Natural Language :: English
Classifier: Operating System :: OS Independent
Classifier: Programming Language :: Python :: 3
Classifier: Topic :: Software Development :: Libraries
Requires-Python: >=3.11
License-File: LICENSE
License-File: AUTHORS
Requires-Dist: matplotlib
Requires-Dist: numpy
